isprimetool/__init__.py
isprimetool-0.1.0.dist-info/METADATA
isprimetool-0.1.0.dist-info/WHEEL
isprimetool-0.1.0.dist-info/top_level.txt
isprimetool-0.1.0.dist-info/RECORD
