Metadata-Version: 2.4
Name: isprimetool
Version: 0.1.0
Summary: a tool to calculate if number is prime
Project-URL: Homepage, https://github.com/toolsmith-auto/isprimetool
Requires-Python: >=3.8
Requires-Dist: pydantic
